cnos_hub/__init__.py
cnos_hub/_base_client.py
cnos_hub/_client.py
cnos_hub/_compat.py
cnos_hub/_constants.py
cnos_hub/_exceptions.py
cnos_hub/_files.py
cnos_hub/_models.py
cnos_hub/_qs.py
cnos_hub/_resource.py
cnos_hub/_response.py
cnos_hub/_streaming.py
cnos_hub/_types.py
cnos_hub/_version.py
cnos_hub/pagination.py
cnos_hub/py.typed
cnos_hub/_utils/__init__.py
cnos_hub/_utils/_compat.py
cnos_hub/_utils/_datetime_parse.py
cnos_hub/_utils/_logs.py
cnos_hub/_utils/_proxy.py
cnos_hub/_utils/_reflection.py
cnos_hub/_utils/_resources_proxy.py
cnos_hub/_utils/_streams.py
cnos_hub/_utils/_sync.py
cnos_hub/_utils/_transform.py
cnos_hub/_utils/_typing.py
cnos_hub/_utils/_utils.py
cnos_hub/lib/.keep
cnos_hub/resources/__init__.py
cnos_hub/resources/authz.py
cnos_hub/resources/cnos.py
cnos_hub/resources/config_schema.py
cnos_hub/resources/context.py
cnos_hub/resources/me.py
cnos_hub/resources/meta.py
cnos_hub/resources/admin/__init__.py
cnos_hub/resources/admin/admin.py
cnos_hub/resources/admin/api_keys/__init__.py
cnos_hub/resources/admin/api_keys/api_keys.py
cnos_hub/resources/admin/api_keys/key.py
cnos_hub/resources/admin/orgs/__init__.py
cnos_hub/resources/admin/orgs/api_keys.py
cnos_hub/resources/admin/orgs/history.py
cnos_hub/resources/admin/orgs/members.py
cnos_hub/resources/admin/orgs/orgs.py
cnos_hub/resources/admin/projects/__init__.py
cnos_hub/resources/admin/projects/api_keys.py
cnos_hub/resources/admin/projects/members.py
cnos_hub/resources/admin/projects/project.py
cnos_hub/resources/admin/projects/projects.py
cnos_hub/resources/api_keys/__init__.py
cnos_hub/resources/api_keys/api_keys.py
cnos_hub/resources/api_keys/key.py
cnos_hub/resources/projects/__init__.py
cnos_hub/resources/projects/budgets.py
cnos_hub/resources/projects/config.py
cnos_hub/resources/projects/events.py
cnos_hub/resources/projects/execute.py
cnos_hub/resources/projects/files.py
cnos_hub/resources/projects/projects.py
cnos_hub/resources/projects/tasks.py
cnos_hub-0.3.0.dist-info/METADATA
cnos_hub-0.3.0.dist-info/WHEEL
cnos_hub-0.3.0.dist-info/licenses/LICENSE
cnos_hub-0.3.0.dist-info/RECORD
